sev_snp_measure-0.0.12.dist-info/licenses/LICENSE
sevsnpmeasure/__init__.py
sevsnpmeasure/cli.py
sevsnpmeasure/gctx.py
sevsnpmeasure/guest.py
sevsnpmeasure/id_block.py
sevsnpmeasure/ovmf.py
sevsnpmeasure/sev_hashes.py
sevsnpmeasure/sev_mode.py
sevsnpmeasure/vcpu_types.py
sevsnpmeasure/vmm_types.py
sevsnpmeasure/vmsa.py
sev_snp_measure-0.0.12.dist-info/METADATA
sev_snp_measure-0.0.12.dist-info/WHEEL
sev_snp_measure-0.0.12.dist-info/entry_points.txt
sev_snp_measure-0.0.12.dist-info/top_level.txt
sev_snp_measure-0.0.12.dist-info/RECORD
