Metadata-Version: 2.4
Name: sev-snp-measure
Version: 0.0.12
Summary: Calculate expected measurement of an AMD SEV/SEV-ES/SEV-SNP guest VM for confidential computing
Home-page: https://github.com/virtee/sev-snp-measure
Author: Dov Murik
Author-email: dov.murik@gmail.com
Project-URL: Bug Tracker, https://github.com/virtee/sev-snp-measure/issues
Classifier: Development Status :: 4 - Beta
Classifier: Intended Audience :: Developers
Classifier: License :: OSI Approved :: Apache Software License
Classifier: Programming Language :: Python :: 3
Classifier: Operating System :: OS Independent
Classifier: Topic :: Security
Classifier: Topic :: Software Development :: Libraries
Requires-Python: >=3.7
License-File: LICENSE
Requires-Dist: cryptography>=39.0.1
Dynamic: license-file
